ipv6offset/__init__.py
ipv6offset/ipv6offset.py
ipv6offset-2.0.0.dist-info/LICENSE
ipv6offset-2.0.0.dist-info/METADATA
ipv6offset-2.0.0.dist-info/WHEEL
ipv6offset-2.0.0.dist-info/entry_points.txt
ipv6offset-2.0.0.dist-info/top_level.txt
ipv6offset-2.0.0.dist-info/RECORD
