Metadata-Version: 2.1
Name: ipv6offset
Version: 2.0.0
Summary: A Simple Tool To Find The IPv6 Address Offset For A Given IPv6.
Author: VietDuc19
License: GPLv3
Keywords: IPv6 offset
Classifier: Programming Language :: Python :: 3
Classifier: License :: OSI Approved :: GNU General Public License v3 (GPLv3)
Classifier: Operating System :: OS Independent
License-File: LICENSE
Requires-Dist: netaddr
